nnpp/__init__.py
nnpp/cli.py
nnpp/nnpp.py
nnpp-0.0.2.dist-info/AUTHORS.rst
nnpp-0.0.2.dist-info/METADATA
nnpp-0.0.2.dist-info/WHEEL
nnpp-0.0.2.dist-info/entry_points.txt
nnpp-0.0.2.dist-info/top_level.txt
nnpp-0.0.2.dist-info/RECORD
