Metadata-Version: 2.1
Name: nnpp
Version: 0.0.2
Summary: Neural Network Pre Processing Collection
Home-page: https://github.com/gazlln/nnpp
Author: Gareth Long
Author-email: gazlong@me.com
License: UNKNOWN
Keywords: nnpp
Platform: UNKNOWN
Classifier: Development Status :: 2 - Pre-Alpha
Classifier: Intended Audience :: Developers
Classifier: Natural Language :: English
Classifier: Programming Language :: Python :: 2
Classifier: Programming Language :: Python :: 2.7
Classifier: Programming Language :: Python :: 3
Classifier: Programming Language :: Python :: 3.4
Classifier: Programming Language :: Python :: 3.5
Classifier: Programming Language :: Python :: 3.6
Classifier: Programming Language :: Python :: 3.7
Requires-Dist: Click
